{
  "groups": [
    {
      "name": "spring.data.mongodb",
      "type": "com.mongodb.partreplication.configuration.MongoProperties",
      "sourceType": "com.mongodb.partreplication.configuration.MongoProperties"
    }
  ],
  "properties": [
    {
      "name": "spring.data.mongodb.ignore-databases",
      "type": "java.util.List<java.lang.String>",
      "sourceType": "com.mongodb.partreplication.configuration.MongoProperties"
    },
    {
      "name": "spring.data.mongodb.include-databases",
      "type": "java.util.List<java.lang.String>",
      "sourceType": "com.mongodb.partreplication.configuration.MongoProperties"
    }
  ],
  "hints": [],
  "ignored": {
    "properties": []
  }
}